{
    "www.onepetro.org": 1591,
    "www.sciencedirect.com": 835,
    "adsabs.harvard.edu": 310,
    "link.springer.com": 239,
    "library.seg.org": 208,
    "scholar.google.com": 192,
    "www.earthdoc.org": 154,
    "patents.google.com": 139,
    "onlinelibrary.wiley.com": 105,
    "pubs.acs.org": 104,
    "www.researchgate.net": 77,
    "archives.datapages.com": 76,
    "ieeexplore.ieee.org": 55,
    "pubs.geoscienceworld.org": 50,
    "www.osti.gov": 41,
    "proceedings.asmedigitalcollection.asme.org": 34,
    "www.tandfonline.com": 34,
    "oaktrust.library.tamu.edu": 33,
    "agupubs.onlinelibrary.wiley.com": 30,
    "www.qscience.com": 30,
    "books.google.com": 27,
    "dspacepre1.library.tamu.edu": 21,
    "pubs.rsc.org": 20,
    "arxiv.org": 15,
    "pdfs.semanticscholar.org": 14,
    "aip.scitation.org": 13,
    "www.nature.com": 13,
    "www.cambridge.org": 12,
    "journals.aps.org": 12,
    "www.inderscienceonline.com": 12,
    "pubsonline.informs.org": 11,
    "epubs.siam.org": 10,
    "pangea.stanford.edu": 10,
    "citeseerx.ist.psu.edu": 10,
    "academic.oup.com": 10,
    "www.egyankosh.ac.in": 10,
    "www.ices.utexas.edu": 10,
    "gsa.confex.com": 9,
    "iopscience.iop.org": 8,
    "www.infona.pl": 8,
    "repositories.lib.utexas.edu": 8,
    "www.iasj.net": 8,
    "ma.ecsdl.org": 7,
    "www.mdpi.com": 7,
    "core.ac.uk": 7,
    "ascelibrary.org": 7,
    "www.dl.begellhouse.com": 7,
    "www.karger.com": 7,
    "www.pnas.org": 6,
    "cloudfront.escholarship.org": 6,
    "journals.sagepub.com": 6,
    "cecas.clemson.edu": 6,
    "www.osapublishing.org": 6,
    "ir.library.oregonstate.edu": 5,
    "science.sciencemag.org": 5,
    "eaas-journal.org": 5,
    "www.searchanddiscovery.com": 5,
    "jes.ecsdl.org": 4,
    "meetings.aps.org": 4,
    "www.worldscientific.com": 4,
    "journals.plos.org": 4,
    "scits.stanford.edu": 4,
    "papers.sae.org": 4,
    "www.netl.doe.gov": 4,
    "search.proquest.com": 4,
    "content.taylorfrancis.com": 3,
    "www.annualreviews.org": 3,
    "www.jstor.org": 3,
    "sp.lyellcollection.org": 3,
    "www.ajsonline.org": 3,
    "dynamicsystems.asmedigitalcollection.asme.org": 3,
    "www.physiology.org": 3,
    "www.hindawi.com": 3,
    "repository.kaust.edu.sa": 3,
    "escholarship.org": 3,
    "pubarchive.lbl.gov": 3,
    "www.academia.edu": 3,
    "www.scielo.br": 3,
    "www.pe.tamu.edu": 3,
    "tigerprints.clemson.edu": 2,
    "dc.engconfintl.org": 2,
    "espace.curtin.edu.au": 2,
    "earth.stanford.edu": 2,
    "www.nrel.gov": 2,
    "www.haematologica.org": 2,
    "pennstate.pure.elsevier.com": 2,
    "utah.pure.elsevier.com": 2,
    "peer.asee.org": 2,
    "www.cell.com": 2,
    "europepmc.org": 2,
    "www.dtic.mil": 2,
    "maeresearch.ucsd.edu": 2,
    "insights.ovid.com": 2,
    "www.ncbi.nlm.nih.gov": 2,
    "www.igi-global.com": 2,
    "energyresources.asmedigitalcollection.asme.org": 2,
    "store.spe.org": 2,
    "uh-ir.tdl.org": 2,
    "www.eaas-journal.org": 2,
    "www.journalofenvironmentalsolutionsforoilgasandmining.com": 2,
    "search.ebscohost.com": 2,
    "researchonline.lshtm.ac.uk": 2,
    "www.cheric.org": 2,
    "www.narcis.nl": 2,
    "repository.tudelft.nl": 2,
    "www.alboran.com": 2,
    "www.cpge.utexas.edu": 2,
    "aseegsw.com": 2,
    "brage.bibsys.no": 2,
    "faculty.engr.utexas.edu": 2,
    "www.afs.enea.it": 2,
    "www.ingentaconnect.com": 2,
    "14.139.40.199": 2,
    "www.slb.com": 2,
    "manufacturingscience.asmedigitalcollection.asme.org": 1,
    "fallmeeting.agu.org": 1,
    "www.jgmaas.com": 1,
    "scripts.iucr.org": 1,
    "www.nae.edu": 1,
    "www.nist.gov": 1,
    "www.iaee.org": 1,
    "carnegieendowment.org": 1,
    "dl.acm.org": 1,
    "www.dem.ist.utl.pt": 1,
    "aslopubs.onlinelibrary.wiley.com": 1,
    "agu.confex.com": 1,
    "care.diabetesjournals.org": 1,
    "hal-imt.archives-ouvertes.fr": 1,
    "cees.stanford.edu": 1,
    "cger.no": 1,
    "www.grand-re2014.org": 1,
    "jlc.jst.go.jp": 1,
    "www.atlasgeoinc.com": 1,
    "www.oit.edu": 1,
    "www.geothermal-energy.org": 1,
    "mines.conference-services.net": 1,
    "www.imwa.info": 1,
    "www.research-collection.ethz.ch": 1,
    "pg.lyellcollection.org": 1,
    "geostats2012.nr.no": 1,
    "www.comsol.pt": 1,
    "ogst.ifpenergiesnouvelles.fr": 1,
    "www.inderscience.com": 1,
    "gigascience.biomedcentral.com": 1,
    "www.frontiersin.org": 1,
    "bmcsystbiol.biomedcentral.com": 1,
    "rspa.royalsocietypublishing.org": 1,
    "netserver.aip.org": 1,
    "digital-library.theiet.org": 1,
    "spiral.imperial.ac.uk": 1,
    "jgmaas.com": 1,
    "kirj.ee": 1,
    "etd.lib.metu.edu.tr": 1,
    "www.cpedm.com": 1,
    "www.scientific.net": 1,
    "www.atmos-chem-phys-discuss.net": 1,
    "prod.sandia.gov": 1,
    "springerplus.springeropen.com": 1,
    "or.nsfc.gov.cn": 1,
    "engineeringresearch.org": 1,
    "synapse.koreamed.org": 1,
    "www.focapo-cpc.org": 1,
    "www.freepatentsonline.com": 1,
    "www.scirp.org": 1,
    "scifedpublishers.com": 1,
    "faculty.kashanu.ac.ir": 1,
    "materialstechnology.asmedigitalcollection.asme.org": 1,
    "cosmosscholars.com": 1,
    "congress.cimne.com": 1,
    "ojs.lexis.srl": 1,
    "www.forskningsdatabasen.dk": 1,
    "www.nt.ntnu.no": 1,
    "www.witpress.com": 1,
    "caos.library.ryerson.ca": 1,
    "bdvets.org": 1,
    "www.jatit.org": 1,
    "nicerjcs.com": 1,
    "www.fortunejournals.com": 1,
    "www.jacsdirectory.com": 1,
    "jacsdirectory.com": 1,
    "copharmacy.nahrainuniv.edu.iq": 1,
    "repository.taibahu.edu.sa": 1,
    "aphyschem.org": 1,
    "dspace.mit.edu": 1,
    "emi2014.mcmaster.ca": 1,
    "ethos.bl.uk": 1,
    "www.cqvip.com": 1,
    "cco.cup.cam.ac.uk": 1,
    "benthamopen.com": 1,
    "www.ogj.com": 1,
    "alboran.status301.net": 1,
    "pure.iiasa.ac.at": 1,
    "alboran.com": 1,
    "www.ij-ee.org": 1,
    "www.shale-gas-information-platform.org": 1,
    "www.ourenergypolicy.org": 1,
    "journals.ametsoc.org": 1,
    "dl.sciencesocieties.org": 1,
    "publications.iodp.org": 1,
    "www.portalabpg.org.br": 1,
    "netl.doe.gov": 1,
    "soilandwater.bee.cornell.edu": 1,
    "ecommons.cornell.edu": 1,
    "smartech.gatech.edu": 1,
    "www.taylorfrancis.com": 1,
    "risk.asmedigitalcollection.asme.org": 1,
    "surveygizmoresponseuploads.s3.amazonaws.com": 1,
    "docs.lib.purdue.edu": 1,
    "www.geoconvention.com": 1,
    "en.cnki.com.cn": 1,
    "papers.ssrn.com": 1,
    "users.ices.utexas.edu": 1,
    "eap.ee": 1,
    "scholarship.rice.edu": 1,
    "www.nsti.org": 1,
    "www.iiis.org": 1,
    "file.scirp.org": 1,
    "www.intechopen.com": 1,
    "www.raschultzunr.net": 1,
    "www.petrosociety.com": 1,
    "www.digitalrocksportal.org": 1,
    "biblio.ugent.be": 1,
    "journals.lww.com": 1,
    "geostatisticslessons.com": 1,
    "science.nichd.nih.gov": 1,
    "www.ccgalberta.com": 1,
    "wwjournals.com": 1,
    "www.redjournal.org": 1,
    "ijpediatrics.com": 1,
    "jemds.com": 1,
    "ijp.iranpath.org": 1,
    "recentscientific.com": 1,
    "www.scopemed.org": 1,
    "www.ijernd.com": 1,
    "ascopubs.org": 1,
    "www.indjst.org": 1,
    "oesi.tamu.edu": 1,
    "www.aade.org": 1,
    "www.theimgfactory.com": 1,
    "www.drillingcontractor.org": 1,
    "hal.archives-ouvertes.fr": 1,
    "www.esaim-m2an.org": 1,
    "open.library.ubc.ca": 1,
    "www.utefrc.org": 1,
    "folk.ntnu.no": 1
}